testops_api/__init__.py
testops_api/api_client.py
testops_api/configuration.py
testops_api/exceptions.py
testops_api/model_utils.py
testops_api/rest.py
testops_api/api/__init__.py
testops_api/api/agent_api.py
testops_api/api/build_api.py
testops_api/api/cache_resource_controller_api.py
testops_api/api/comment_api.py
testops_api/api/custom_field_definition_api.py
testops_api/api/execution_api.py
testops_api/api/execution_export_api.py
testops_api/api/execution_request_api.py
testops_api/api/execution_test_result_api.py
testops_api/api/execution_test_suite_api.py
testops_api/api/file_api.py
testops_api/api/job_api.py
testops_api/api/katalon_recorder_api.py
testops_api/api/label_api.py
testops_api/api/notification_controller_api.py
testops_api/api/organization_trial_request_resource_controller_api.py
testops_api/api/project_api.py
testops_api/api/project_configuration_resource_controller_api.py
testops_api/api/release_api.py
testops_api/api/search_api.py
testops_api/api/smart_scheduler_api.py
testops_api/api/tag_api.py
testops_api/api/task_api.py
testops_api/api/team_api.py
testops_api/api/test_case_api.py
testops_api/api/test_cloud_agent_api.py
testops_api/api/test_cloud_proxy_tunnel_controller_api.py
testops_api/api/test_folder_resource_controller_api.py
testops_api/api/test_object_api.py
testops_api/api/test_plan_api.py
testops_api/api/test_project_api.py
testops_api/api/test_report_api.py
testops_api/api/test_suite_api.py
testops_api/api/user_api.py
testops_api/api/visual_testing_api.py
testops_api/api/web_service_api.py
testops_api/apis/__init__.py
testops_api/model/__init__.py
testops_api/model/access_token_resource.py
testops_api/model/agent_config_resource.py
testops_api/model/agent_resource.py
testops_api/model/baseline_collection_group_resource.py
testops_api/model/baseline_collection_resource.py
testops_api/model/baseline_collection_upload_baselines_resource.py
testops_api/model/baseline_resource.py
testops_api/model/build_info.py
testops_api-1.0.2.dist-info/LICENSE
testops_api-1.0.2.dist-info/METADATA
testops_api-1.0.2.dist-info/WHEEL
testops_api-1.0.2.dist-info/top_level.txt
testops_api-1.0.2.dist-info/RECORD
